README.rst
setup.cfg
setup.py
zipe/__init__.py
zipe/unzip.py
zipe/util.py
zipe/zip.py
zipe.egg-info/PKG-INFO
zipe.egg-info/SOURCES.txt
zipe.egg-info/dependency_links.txt
zipe.egg-info/entry_points.txt
zipe.egg-info/requires.txt
zipe.egg-info/top_level.txt