Metadata-Version: 1.1
Name: zipe
Version: 0.1.3
Summary: A zip utility for cross OS, especially file name encoding problem.
Home-page: https://github.com/jbking/zipe/
Author: MURAOKA Yusuke
Author-email: yusuke@jbking.org
License: MIT
Keywords: zip utility
Platform: UNKNOWN
Classifier: Development Status :: 3 - Alpha
Classifier: Topic :: Utilities
Classifier: License :: OSI Approved :: MIT License
Classifier: Programming Language :: Python :: 3.5
Classifier: Programming Language :: Python :: 3.6
